csbootstrap/__init__.py
csbootstrap/__main__.py
csbootstrap-1.1.0.dist-info/LICENSE.txt
csbootstrap-1.1.0.dist-info/METADATA
csbootstrap-1.1.0.dist-info/WHEEL
csbootstrap-1.1.0.dist-info/entry_points.txt
csbootstrap-1.1.0.dist-info/top_level.txt
csbootstrap-1.1.0.dist-info/RECORD
