Metadata-Version: 2.1
Name: csbootstrap
Version: 1.1.0
Summary: A script for bootstrapping a device in CENTERSIGHT NG
Home-page: https://github.com/deviceinsight/csbootstrap
Author: Stephan Spindler
Author-email: stephan.spindler@device-insight.com
License: Apache 2.0
Platform: UNKNOWN
Requires-Python: >=3, <4
Requires-Dist: requests (>=2.20.1)
Requires-Dist: pyOpenSSL (>=18.0.0)
